{
  "ruleLogicalInfo" : {
    "id" : 5316361,
    "ruleInstanceId" : 0,
    "ruleDesc" : "",
    "execMode" : "report",
    "exitCode" : null,
    "folderId" : 5170941,
    "projectId" : 199081,
    "ruleCode" : "1700649979967",
    "folderName" : "10_Rules",
    "folderType" : "RULE",
    "startTime" : null,
    "endTime" : null,
    "ruleName" : "Recon_ImportSQL_1_1700649979967",
    "displayName" : null,
    "rulePurpose" : "",
    "ruleTemplate" : null,
    "statusName" : null,
    "ruleCreatedBy" : 181338,
    "ruleModifiedBy" : 0,
    "subjectAreaKey" : 0,
    "ruleStatus" : 1,
    "ruleCreateDate" : "2023-11-22 00:00:00",
    "ruleModifiedDate" : null,
    "enterpriseErrorCode" : "",
    "legalEntityId" : 1,
    "subjectAreaName" : null,
    "execNode" : "",
    "children" : null,
    "objVOList" : [ ],
    "tagVOList" : [ ],
    "ruleFlowList" : null,
    "ruleType" : "Warning",
    "auditExecutedByProcess" : null,
    "auditExecutionMedium" : null,
    "auditExecutionMediumName" : null,
    "comments" : null,
    "successMailUsers" : [ ],
    "failureMailUsers" : [ ],
    "successHeader" : "",
    "failureHeader" : "",
    "failureAttFlag" : 0,
    "successAttFlag" : 0,
    "srcConnId" : 96852,
    "trgConnId" : 96852,
    "srcSysGroupId" : 0,
    "trgSysGroupId" : 0,
    "srcConn" : "Oracle_01",
    "trgConn" : "Oracle_01",
    "elapseTime" : 0,
    "parameterId" : "",
    "type" : null,
    "isRuleExit" : null,
    "ruleCreatedByName" : "Samit",
    "projectName" : "WIP_Samit",
    "ruleModifiedByName" : null,
    "ruleClassId" : 5316362,
    "successBody" : "",
    "failureBody" : "",
    "templateId" : 206,
    "templateIdFail" : 206,
    "reportIdList" : [ ],
    "contextInstanceId" : 0,
    "srcConnFlag" : "REGULAR",
    "trgConnFlag" : "REGULAR",
    "degreeOfParallelism" : 0,
    "userComments" : null,
    "templateName" : "Rule Template-Default",
    "templateFailureName" : "Rule Template-Default",
    "objExists" : true
  },
  "rulePhysicalInfo" : {
    "objectName" : null,
    "ruleId" : 5316361,
    "reportRuleClassId" : 0,
    "ruleCId" : 0,
    "classVOList" : [ {
      "classId" : 3,
      "name" : null,
      "ruleClassId" : 5316362,
      "connType" : "",
      "execMode" : "report",
      "index" : 1,
      "classRun" : "com.ice.bpel.CompareData",
      "vid" : "CompareData11",
      "classObjName" : "ICE_1700634810045",
      "queryBuilderXML" : null,
      "connId" : 0,
      "resultType" : "expression",
      "connName" : null,
      "connUrl" : null,
      "connFullUrl" : null,
      "sysGrpId" : 0,
      "ruleId" : 0,
      "ruleName" : null,
      "ruleParameter" : null,
      "srcTrgMaplist" : [ {
        "colMapId" : 5316409,
        "srcColId" : 5316386,
        "trgColId" : 5316408,
        "colMapType" : "join",
        "srcColName" : "staffid",
        "tgtColName" : "cnt",
        "colMapExpr" : "cnt=staffid",
        "srcTrgColMapVisible" : 0,
        "displayIndex" : 0
      } ],
      "exprlist" : [ {
        "exprID" : 5316410,
        "exprLogID" : 0,
        "exprName" : "e_staffid",
        "expression" : "S.staffid == null",
        "result" : "Pass",
        "exprType" : "5",
        "exprVisible" : 1,
        "exprIndex" : 0,
        "ruleId" : 5316361,
        "ruleInstanceId" : 0,
        "ruleClassId" : 5316362,
        "ruleName" : null,
        "trueCount" : null,
        "falseCount" : null,
        "errCount" : null,
        "exprOrg" : "S.staffid == null",
        "tc" : null,
        "fc" : null,
        "er" : null,
        "name" : null,
        "ve" : 0,
        "exporg" : null
      }, {
        "exprID" : 5316411,
        "exprLogID" : 0,
        "exprName" : "e_sex",
        "expression" : "S.sex == null",
        "result" : "Pass",
        "exprType" : "5",
        "exprVisible" : 1,
        "exprIndex" : 1,
        "ruleId" : 5316361,
        "ruleInstanceId" : 0,
        "ruleClassId" : 5316362,
        "ruleName" : null,
        "trueCount" : null,
        "falseCount" : null,
        "errCount" : null,
        "exprOrg" : "S.sex == null",
        "tc" : null,
        "fc" : null,
        "er" : null,
        "name" : null,
        "ve" : 0,
        "exporg" : null
      }, {
        "exprID" : 5316412,
        "exprLogID" : 0,
        "exprName" : "e_jobcode",
        "expression" : "S.jobcode == null",
        "result" : "Pass",
        "exprType" : "5",
        "exprVisible" : 1,
        "exprIndex" : 2,
        "ruleId" : 5316361,
        "ruleInstanceId" : 0,
        "ruleClassId" : 5316362,
        "ruleName" : null,
        "trueCount" : null,
        "falseCount" : null,
        "errCount" : null,
        "exprOrg" : "S.jobcode == null",
        "tc" : null,
        "fc" : null,
        "er" : null,
        "name" : null,
        "ve" : 0,
        "exporg" : null
      }, {
        "exprID" : 5316413,
        "exprLogID" : 0,
        "exprName" : "e_company",
        "expression" : "S.company == null",
        "result" : "Pass",
        "exprType" : "5",
        "exprVisible" : 1,
        "exprIndex" : 3,
        "ruleId" : 5316361,
        "ruleInstanceId" : 0,
        "ruleClassId" : 5316362,
        "ruleName" : null,
        "trueCount" : null,
        "falseCount" : null,
        "errCount" : null,
        "exprOrg" : "S.company == null",
        "tc" : null,
        "fc" : null,
        "er" : null,
        "name" : null,
        "ve" : 0,
        "exporg" : null
      }, {
        "exprID" : 5316414,
        "exprLogID" : 0,
        "exprName" : "e_salary",
        "expression" : "S.salary == null",
        "result" : "Pass",
        "exprType" : "5",
        "exprVisible" : 1,
        "exprIndex" : 4,
        "ruleId" : 5316361,
        "ruleInstanceId" : 0,
        "ruleClassId" : 5316362,
        "ruleName" : null,
        "trueCount" : null,
        "falseCount" : null,
        "errCount" : null,
        "exprOrg" : "S.salary == null",
        "tc" : null,
        "fc" : null,
        "er" : null,
        "name" : null,
        "ve" : 0,
        "exporg" : null
      }, {
        "exprID" : 5316415,
        "exprLogID" : 0,
        "exprName" : "e_bonus",
        "expression" : "S.bonus == null",
        "result" : "Pass",
        "exprType" : "5",
        "exprVisible" : 1,
        "exprIndex" : 5,
        "ruleId" : 5316361,
        "ruleInstanceId" : 0,
        "ruleClassId" : 5316362,
        "ruleName" : null,
        "trueCount" : null,
        "falseCount" : null,
        "errCount" : null,
        "exprOrg" : "S.bonus == null",
        "tc" : null,
        "fc" : null,
        "er" : null,
        "name" : null,
        "ve" : 0,
        "exporg" : null
      }, {
        "exprID" : 5316416,
        "exprLogID" : 0,
        "exprName" : "e_comm",
        "expression" : "S.comm == null",
        "result" : "Pass",
        "exprType" : "5",
        "exprVisible" : 1,
        "exprIndex" : 6,
        "ruleId" : 5316361,
        "ruleInstanceId" : 0,
        "ruleClassId" : 5316362,
        "ruleName" : null,
        "trueCount" : null,
        "falseCount" : null,
        "errCount" : null,
        "exprOrg" : "S.comm == null",
        "tc" : null,
        "fc" : null,
        "er" : null,
        "name" : null,
        "ve" : 0,
        "exporg" : null
      }, {
        "exprID" : 5316417,
        "exprLogID" : 0,
        "exprName" : "e_totalsalary",
        "expression" : "S.totalsalary == null",
        "result" : "Pass",
        "exprType" : "5",
        "exprVisible" : 1,
        "exprIndex" : 7,
        "ruleId" : 5316361,
        "ruleInstanceId" : 0,
        "ruleClassId" : 5316362,
        "ruleName" : null,
        "trueCount" : null,
        "falseCount" : null,
        "errCount" : null,
        "exprOrg" : "S.totalsalary == null",
        "tc" : null,
        "fc" : null,
        "er" : null,
        "name" : null,
        "ve" : 0,
        "exporg" : null
      }, {
        "exprID" : 5316418,
        "exprLogID" : 0,
        "exprName" : "e_birthd",
        "expression" : "S.birthd == null",
        "result" : "Pass",
        "exprType" : "5",
        "exprVisible" : 1,
        "exprIndex" : 8,
        "ruleId" : 5316361,
        "ruleInstanceId" : 0,
        "ruleClassId" : 5316362,
        "ruleName" : null,
        "trueCount" : null,
        "falseCount" : null,
        "errCount" : null,
        "exprOrg" : "S.birthd == null",
        "tc" : null,
        "fc" : null,
        "er" : null,
        "name" : null,
        "ve" : 0,
        "exporg" : null
      }, {
        "exprID" : 5316419,
        "exprLogID" : 0,
        "exprName" : "e_hired",
        "expression" : "S.hired == null",
        "result" : "Pass",
        "exprType" : "5",
        "exprVisible" : 1,
        "exprIndex" : 9,
        "ruleId" : 5316361,
        "ruleInstanceId" : 0,
        "ruleClassId" : 5316362,
        "ruleName" : null,
        "trueCount" : null,
        "falseCount" : null,
        "errCount" : null,
        "exprOrg" : "S.hired == null",
        "tc" : null,
        "fc" : null,
        "er" : null,
        "name" : null,
        "ve" : 0,
        "exporg" : null
      }, {
        "exprID" : 5316420,
        "exprLogID" : 0,
        "exprName" : "e_lname",
        "expression" : "S.lname == null",
        "result" : "Pass",
        "exprType" : "5",
        "exprVisible" : 1,
        "exprIndex" : 10,
        "ruleId" : 5316361,
        "ruleInstanceId" : 0,
        "ruleClassId" : 5316362,
        "ruleName" : null,
        "trueCount" : null,
        "falseCount" : null,
        "errCount" : null,
        "exprOrg" : "S.lname == null",
        "tc" : null,
        "fc" : null,
        "er" : null,
        "name" : null,
        "ve" : 0,
        "exporg" : null
      }, {
        "exprID" : 5316421,
        "exprLogID" : 0,
        "exprName" : "e_fname",
        "expression" : "S.fname == null",
        "result" : "Pass",
        "exprType" : "5",
        "exprVisible" : 1,
        "exprIndex" : 11,
        "ruleId" : 5316361,
        "ruleInstanceId" : 0,
        "ruleClassId" : 5316362,
        "ruleName" : null,
        "trueCount" : null,
        "falseCount" : null,
        "errCount" : null,
        "exprOrg" : "S.fname == null",
        "tc" : null,
        "fc" : null,
        "er" : null,
        "name" : null,
        "ve" : 0,
        "exporg" : null
      }, {
        "exprID" : 5316422,
        "exprLogID" : 0,
        "exprName" : "e_address",
        "expression" : "S.address == null",
        "result" : "Pass",
        "exprType" : "5",
        "exprVisible" : 1,
        "exprIndex" : 12,
        "ruleId" : 5316361,
        "ruleInstanceId" : 0,
        "ruleClassId" : 5316362,
        "ruleName" : null,
        "trueCount" : null,
        "falseCount" : null,
        "errCount" : null,
        "exprOrg" : "S.address == null",
        "tc" : null,
        "fc" : null,
        "er" : null,
        "name" : null,
        "ve" : 0,
        "exporg" : null
      }, {
        "exprID" : 5316423,
        "exprLogID" : 0,
        "exprName" : "e_city",
        "expression" : "S.city == null",
        "result" : "Pass",
        "exprType" : "5",
        "exprVisible" : 1,
        "exprIndex" : 13,
        "ruleId" : 5316361,
        "ruleInstanceId" : 0,
        "ruleClassId" : 5316362,
        "ruleName" : null,
        "trueCount" : null,
        "falseCount" : null,
        "errCount" : null,
        "exprOrg" : "S.city == null",
        "tc" : null,
        "fc" : null,
        "er" : null,
        "name" : null,
        "ve" : 0,
        "exporg" : null
      }, {
        "exprID" : 5316424,
        "exprLogID" : 0,
        "exprName" : "e_state",
        "expression" : "S.state == null",
        "result" : "Pass",
        "exprType" : "5",
        "exprVisible" : 1,
        "exprIndex" : 14,
        "ruleId" : 5316361,
        "ruleInstanceId" : 0,
        "ruleClassId" : 5316362,
        "ruleName" : null,
        "trueCount" : null,
        "falseCount" : null,
        "errCount" : null,
        "exprOrg" : "S.state == null",
        "tc" : null,
        "fc" : null,
        "er" : null,
        "name" : null,
        "ve" : 0,
        "exporg" : null
      }, {
        "exprID" : 5316425,
        "exprLogID" : 0,
        "exprName" : "e_hphone",
        "expression" : "S.hphone == null",
        "result" : "Pass",
        "exprType" : "5",
        "exprVisible" : 1,
        "exprIndex" : 15,
        "ruleId" : 5316361,
        "ruleInstanceId" : 0,
        "ruleClassId" : 5316362,
        "ruleName" : null,
        "trueCount" : null,
        "falseCount" : null,
        "errCount" : null,
        "exprOrg" : "S.hphone == null",
        "tc" : null,
        "fc" : null,
        "er" : null,
        "name" : null,
        "ve" : 0,
        "exporg" : null
      }, {
        "exprID" : 5316426,
        "exprLogID" : 0,
        "exprName" : "e_ssn",
        "expression" : "S.ssn == null",
        "result" : "Pass",
        "exprType" : "5",
        "exprVisible" : 1,
        "exprIndex" : 16,
        "ruleId" : 5316361,
        "ruleInstanceId" : 0,
        "ruleClassId" : 5316362,
        "ruleName" : null,
        "trueCount" : null,
        "falseCount" : null,
        "errCount" : null,
        "exprOrg" : "S.ssn == null",
        "tc" : null,
        "fc" : null,
        "er" : null,
        "name" : null,
        "ve" : 0,
        "exporg" : null
      } ],
      "derivedexprlist" : null,
      "paramsVOLst" : [ {
        "ruleClsPropID" : 5316365,
        "paramId" : 9,
        "paramMethod" : "setSourceObject",
        "paramValue" : "GetData11",
        "srcTrgTbllist" : null,
        "fileContent" : null
      }, {
        "ruleClsPropID" : 5316366,
        "paramId" : 10,
        "paramMethod" : "setTargetObject",
        "paramValue" : "GetData21",
        "srcTrgTbllist" : null,
        "fileContent" : null
      }, {
        "ruleClsPropID" : 5316367,
        "paramId" : 22,
        "paramMethod" : "setMaxRowCount",
        "paramValue" : "{{Rows}}",
        "srcTrgTbllist" : null,
        "fileContent" : null
      }, {
        "ruleClsPropID" : 5316368,
        "paramId" : 23,
        "paramMethod" : "setMaxErrorCount",
        "paramValue" : "",
        "srcTrgTbllist" : null,
        "fileContent" : null
      }, {
        "ruleClsPropID" : 5316369,
        "paramId" : 24,
        "paramMethod" : "setShowErrorData",
        "paramValue" : "No",
        "srcTrgTbllist" : null,
        "fileContent" : null
      }, {
        "ruleClsPropID" : 5316370,
        "paramId" : 72,
        "paramMethod" : "setTimeOut",
        "paramValue" : "",
        "srcTrgTbllist" : null,
        "fileContent" : null
      }, {
        "ruleClsPropID" : 5316371,
        "paramId" : 73,
        "paramMethod" : "setLoadDataFlag",
        "paramValue" : "No",
        "srcTrgTbllist" : null,
        "fileContent" : null
      }, {
        "ruleClsPropID" : 5316372,
        "paramId" : 465,
        "paramMethod" : "setReportXlsx",
        "paramValue" : "No",
        "srcTrgTbllist" : null,
        "fileContent" : null
      }, {
        "ruleClsPropID" : 5316373,
        "paramId" : 530,
        "paramMethod" : "setThresholdFlag",
        "paramValue" : "false",
        "srcTrgTbllist" : null,
        "fileContent" : null
      }, {
        "ruleClsPropID" : 5316374,
        "paramId" : 531,
        "paramMethod" : "setThresholdExpression",
        "paramValue" : "",
        "srcTrgTbllist" : [ ],
        "fileContent" : null
      }, {
        "ruleClsPropID" : 5316376,
        "paramId" : 798,
        "paramMethod" : "setEngineType",
        "paramValue" : "V8",
        "srcTrgTbllist" : null,
        "fileContent" : null
      } ],
      "bigDataExecMode" : null,
      "srcConnServer" : null,
      "trgConnServer" : null,
      "srcConnExecMode" : null,
      "trgConnExecMode" : null,
      "thresholdFlag" : null,
      "thresholdExpression" : null
    }, {
      "classId" : 1,
      "name" : null,
      "ruleClassId" : 5316363,
      "connType" : "DATABASE",
      "execMode" : "report",
      "index" : 0,
      "classRun" : "com.ice.bpel.GetData",
      "vid" : "GetData11",
      "classObjName" : "ICE_1700634810045",
      "queryBuilderXML" : null,
      "connId" : 96852,
      "resultType" : "expression",
      "connName" : null,
      "connUrl" : null,
      "connFullUrl" : null,
      "sysGrpId" : 0,
      "ruleId" : 0,
      "ruleName" : null,
      "ruleParameter" : null,
      "srcTrgMaplist" : [ ],
      "exprlist" : [ ],
      "derivedexprlist" : null,
      "paramsVOLst" : [ {
        "ruleClsPropID" : 5316377,
        "paramId" : 6,
        "paramMethod" : "setQueryString",
        "paramValue" : "select * from REGRESSION_DATABASE.STAFF",
        "srcTrgTbllist" : [ {
          "srcTgtColId" : 5316386,
          "ruleClsPropId" : 5316377,
          "srcTrgColName" : "staffid",
          "srcTrgColDataType" : "VARCHAR2",
          "colFlagType" : "src",
          "srcTrgColVisible" : 0,
          "joinList" : null,
          "mapColName" : null,
          "colFormat" : "",
          "displayIndex" : 0
        }, {
          "srcTgtColId" : 5316387,
          "ruleClsPropId" : 5316377,
          "srcTrgColName" : "sex",
          "srcTrgColDataType" : "CHAR",
          "colFlagType" : "src",
          "srcTrgColVisible" : 0,
          "joinList" : null,
          "mapColName" : null,
          "colFormat" : "",
          "displayIndex" : 0
        }, {
          "srcTgtColId" : 5316388,
          "ruleClsPropId" : 5316377,
          "srcTrgColName" : "jobcode",
          "srcTrgColDataType" : "VARCHAR2",
          "colFlagType" : "src",
          "srcTrgColVisible" : 0,
          "joinList" : null,
          "mapColName" : null,
          "colFormat" : "",
          "displayIndex" : 0
        }, {
          "srcTgtColId" : 5316389,
          "ruleClsPropId" : 5316377,
          "srcTrgColName" : "company",
          "srcTrgColDataType" : "VARCHAR2",
          "colFlagType" : "src",
          "srcTrgColVisible" : 0,
          "joinList" : null,
          "mapColName" : null,
          "colFormat" : "",
          "displayIndex" : 0
        }, {
          "srcTgtColId" : 5316390,
          "ruleClsPropId" : 5316377,
          "srcTrgColName" : "salary",
          "srcTrgColDataType" : "NUMBER",
          "colFlagType" : "src",
          "srcTrgColVisible" : 0,
          "joinList" : null,
          "mapColName" : null,
          "colFormat" : "",
          "displayIndex" : 0
        }, {
          "srcTgtColId" : 5316391,
          "ruleClsPropId" : 5316377,
          "srcTrgColName" : "bonus",
          "srcTrgColDataType" : "NUMBER",
          "colFlagType" : "src",
          "srcTrgColVisible" : 0,
          "joinList" : null,
          "mapColName" : null,
          "colFormat" : "",
          "displayIndex" : 0
        }, {
          "srcTgtColId" : 5316392,
          "ruleClsPropId" : 5316377,
          "srcTrgColName" : "comm",
          "srcTrgColDataType" : "NUMBER",
          "colFlagType" : "src",
          "srcTrgColVisible" : 0,
          "joinList" : null,
          "mapColName" : null,
          "colFormat" : "",
          "displayIndex" : 0
        }, {
          "srcTgtColId" : 5316393,
          "ruleClsPropId" : 5316377,
          "srcTrgColName" : "totalsalary",
          "srcTrgColDataType" : "NUMBER",
          "colFlagType" : "src",
          "srcTrgColVisible" : 0,
          "joinList" : null,
          "mapColName" : null,
          "colFormat" : "",
          "displayIndex" : 0
        }, {
          "srcTgtColId" : 5316394,
          "ruleClsPropId" : 5316377,
          "srcTrgColName" : "birthd",
          "srcTrgColDataType" : "DATE",
          "colFlagType" : "src",
          "srcTrgColVisible" : 0,
          "joinList" : null,
          "mapColName" : null,
          "colFormat" : "",
          "displayIndex" : 0
        }, {
          "srcTgtColId" : 5316395,
          "ruleClsPropId" : 5316377,
          "srcTrgColName" : "hired",
          "srcTrgColDataType" : "TIMESTAMP",
          "colFlagType" : "src",
          "srcTrgColVisible" : 0,
          "joinList" : null,
          "mapColName" : null,
          "colFormat" : "",
          "displayIndex" : 0
        }, {
          "srcTgtColId" : 5316396,
          "ruleClsPropId" : 5316377,
          "srcTrgColName" : "lname",
          "srcTrgColDataType" : "VARCHAR2",
          "colFlagType" : "src",
          "srcTrgColVisible" : 0,
          "joinList" : null,
          "mapColName" : null,
          "colFormat" : "",
          "displayIndex" : 0
        }, {
          "srcTgtColId" : 5316397,
          "ruleClsPropId" : 5316377,
          "srcTrgColName" : "fname",
          "srcTrgColDataType" : "VARCHAR2",
          "colFlagType" : "src",
          "srcTrgColVisible" : 0,
          "joinList" : null,
          "mapColName" : null,
          "colFormat" : "",
          "displayIndex" : 0
        }, {
          "srcTgtColId" : 5316398,
          "ruleClsPropId" : 5316377,
          "srcTrgColName" : "address",
          "srcTrgColDataType" : "VARCHAR2",
          "colFlagType" : "src",
          "srcTrgColVisible" : 0,
          "joinList" : null,
          "mapColName" : null,
          "colFormat" : "",
          "displayIndex" : 0
        }, {
          "srcTgtColId" : 5316399,
          "ruleClsPropId" : 5316377,
          "srcTrgColName" : "city",
          "srcTrgColDataType" : "VARCHAR2",
          "colFlagType" : "src",
          "srcTrgColVisible" : 0,
          "joinList" : null,
          "mapColName" : null,
          "colFormat" : "",
          "displayIndex" : 0
        }, {
          "srcTgtColId" : 5316400,
          "ruleClsPropId" : 5316377,
          "srcTrgColName" : "state",
          "srcTrgColDataType" : "VARCHAR2",
          "colFlagType" : "src",
          "srcTrgColVisible" : 0,
          "joinList" : null,
          "mapColName" : null,
          "colFormat" : "",
          "displayIndex" : 0
        }, {
          "srcTgtColId" : 5316401,
          "ruleClsPropId" : 5316377,
          "srcTrgColName" : "hphone",
          "srcTrgColDataType" : "VARCHAR2",
          "colFlagType" : "src",
          "srcTrgColVisible" : 0,
          "joinList" : null,
          "mapColName" : null,
          "colFormat" : "",
          "displayIndex" : 0
        }, {
          "srcTgtColId" : 5316402,
          "ruleClsPropId" : 5316377,
          "srcTrgColName" : "ssn",
          "srcTrgColDataType" : "NUMBER",
          "colFlagType" : "src",
          "srcTrgColVisible" : 0,
          "joinList" : null,
          "mapColName" : null,
          "colFormat" : "",
          "displayIndex" : 0
        } ],
        "fileContent" : null
      }, {
        "ruleClsPropID" : 5316379,
        "paramId" : 16,
        "paramMethod" : "setConnId",
        "paramValue" : "96852",
        "srcTrgTbllist" : null,
        "fileContent" : null
      }, {
        "ruleClsPropID" : 5316380,
        "paramId" : 337,
        "paramMethod" : "setIsStoredProcedure",
        "paramValue" : "false",
        "srcTrgTbllist" : null,
        "fileContent" : null
      }, {
        "ruleClsPropID" : 5316381,
        "paramId" : 82,
        "paramMethod" : "setAppendOrderBy",
        "paramValue" : "false",
        "srcTrgTbllist" : null,
        "fileContent" : null
      }, {
        "ruleClsPropID" : 5316382,
        "paramId" : 84,
        "paramMethod" : "setOrderByStr",
        "paramValue" : "",
        "srcTrgTbllist" : [ ],
        "fileContent" : null
      }, {
        "ruleClsPropID" : 5316384,
        "paramId" : 83,
        "paramMethod" : "setColumnsMInfo",
        "paramValue" : "staffid^~^12^~^VARCHAR2^~^2000^~^1$~$sex^~^1^~^CHAR^~^1^~^2$~$jobcode^~^12^~^VARCHAR2^~^2000^~^3$~$company^~^12^~^VARCHAR2^~^2000^~^4$~$salary^~^2^~^NUMBER^~^0^~^5$~$bonus^~^2^~^NUMBER^~^20^~^6$~$comm^~^2^~^NUMBER^~^20^~^7$~$totalsalary^~^2^~^NUMBER^~^20^~^8$~$birthd^~^93^~^DATE^~^0^~^9$~$hired^~^93^~^TIMESTAMP^~^0^~^10$~$lname^~^12^~^VARCHAR2^~^2000^~^11$~$fname^~^12^~^VARCHAR2^~^2000^~^12$~$address^~^12^~^VARCHAR2^~^2000^~^13$~$city^~^12^~^VARCHAR2^~^2000^~^14$~$state^~^12^~^VARCHAR2^~^2000^~^15$~$hphone^~^12^~^VARCHAR2^~^2000^~^16$~$ssn^~^2^~^NUMBER^~^20^~^17",
        "srcTrgTbllist" : [ ],
        "fileContent" : null
      }, {
        "ruleClsPropID" : 5316385,
        "paramId" : 404,
        "paramMethod" : "setIsMultipleOutVaiables",
        "paramValue" : "false",
        "srcTrgTbllist" : null,
        "fileContent" : null
      } ],
      "bigDataExecMode" : null,
      "srcConnServer" : null,
      "trgConnServer" : null,
      "srcConnExecMode" : null,
      "trgConnExecMode" : null,
      "thresholdFlag" : null,
      "thresholdExpression" : null
    }, {
      "classId" : 1,
      "name" : null,
      "ruleClassId" : 5316364,
      "connType" : "DATABASE",
      "execMode" : "report",
      "index" : 0,
      "classRun" : "com.ice.bpel.GetData",
      "vid" : "GetData21",
      "classObjName" : "ICE_1700634810045",
      "queryBuilderXML" : null,
      "connId" : 96852,
      "resultType" : "expression",
      "connName" : null,
      "connUrl" : null,
      "connFullUrl" : null,
      "sysGrpId" : 0,
      "ruleId" : 0,
      "ruleName" : null,
      "ruleParameter" : null,
      "srcTrgMaplist" : [ ],
      "exprlist" : [ ],
      "derivedexprlist" : null,
      "paramsVOLst" : [ {
        "ruleClsPropID" : 5316403,
        "paramId" : 6,
        "paramMethod" : "setQueryString",
        "paramValue" : "select 1 as cnt from dual",
        "srcTrgTbllist" : [ {
          "srcTgtColId" : 5316408,
          "ruleClsPropId" : 5316403,
          "srcTrgColName" : "cnt",
          "srcTrgColDataType" : "String",
          "colFlagType" : "tgt",
          "srcTrgColVisible" : 0,
          "joinList" : null,
          "mapColName" : null,
          "colFormat" : "",
          "displayIndex" : 0
        } ],
        "fileContent" : null
      }, {
        "ruleClsPropID" : 5316405,
        "paramId" : 83,
        "paramMethod" : "setColumnsMInfo",
        "paramValue" : "cnt^~^12^~^String^~^20^~^1",
        "srcTrgTbllist" : [ ],
        "fileContent" : null
      }, {
        "ruleClsPropID" : 5316406,
        "paramId" : 16,
        "paramMethod" : "setConnId",
        "paramValue" : "96852",
        "srcTrgTbllist" : null,
        "fileContent" : null
      }, {
        "ruleClsPropID" : 5316407,
        "paramId" : 82,
        "paramMethod" : "setAppendOrderBy",
        "paramValue" : "false",
        "srcTrgTbllist" : null,
        "fileContent" : null
      } ],
      "bigDataExecMode" : null,
      "srcConnServer" : null,
      "trgConnServer" : null,
      "srcConnExecMode" : null,
      "trgConnExecMode" : null,
      "thresholdFlag" : null,
      "thresholdExpression" : null
    } ],
    "srcTrgTbllist" : [ {
      "srcTgtColId" : 5316386,
      "ruleClsPropId" : 5316377,
      "srcTrgColName" : "staffid",
      "srcTrgColDataType" : "VARCHAR2",
      "colFlagType" : "src",
      "srcTrgColVisible" : 0,
      "joinList" : null,
      "mapColName" : "staffid",
      "colFormat" : "",
      "displayIndex" : 0
    }, {
      "srcTgtColId" : 5316387,
      "ruleClsPropId" : 5316377,
      "srcTrgColName" : "sex",
      "srcTrgColDataType" : "CHAR",
      "colFlagType" : "src",
      "srcTrgColVisible" : 0,
      "joinList" : null,
      "mapColName" : "sex",
      "colFormat" : "",
      "displayIndex" : 0
    }, {
      "srcTgtColId" : 5316388,
      "ruleClsPropId" : 5316377,
      "srcTrgColName" : "jobcode",
      "srcTrgColDataType" : "VARCHAR2",
      "colFlagType" : "src",
      "srcTrgColVisible" : 0,
      "joinList" : null,
      "mapColName" : "jobcode",
      "colFormat" : "",
      "displayIndex" : 0
    }, {
      "srcTgtColId" : 5316389,
      "ruleClsPropId" : 5316377,
      "srcTrgColName" : "company",
      "srcTrgColDataType" : "VARCHAR2",
      "colFlagType" : "src",
      "srcTrgColVisible" : 0,
      "joinList" : null,
      "mapColName" : "company",
      "colFormat" : "",
      "displayIndex" : 0
    }, {
      "srcTgtColId" : 5316390,
      "ruleClsPropId" : 5316377,
      "srcTrgColName" : "salary",
      "srcTrgColDataType" : "NUMBER",
      "colFlagType" : "src",
      "srcTrgColVisible" : 0,
      "joinList" : null,
      "mapColName" : "salary",
      "colFormat" : "",
      "displayIndex" : 0
    }, {
      "srcTgtColId" : 5316391,
      "ruleClsPropId" : 5316377,
      "srcTrgColName" : "bonus",
      "srcTrgColDataType" : "NUMBER",
      "colFlagType" : "src",
      "srcTrgColVisible" : 0,
      "joinList" : null,
      "mapColName" : "bonus",
      "colFormat" : "",
      "displayIndex" : 0
    }, {
      "srcTgtColId" : 5316392,
      "ruleClsPropId" : 5316377,
      "srcTrgColName" : "comm",
      "srcTrgColDataType" : "NUMBER",
      "colFlagType" : "src",
      "srcTrgColVisible" : 0,
      "joinList" : null,
      "mapColName" : "comm",
      "colFormat" : "",
      "displayIndex" : 0
    }, {
      "srcTgtColId" : 5316393,
      "ruleClsPropId" : 5316377,
      "srcTrgColName" : "totalsalary",
      "srcTrgColDataType" : "NUMBER",
      "colFlagType" : "src",
      "srcTrgColVisible" : 0,
      "joinList" : null,
      "mapColName" : "totalsalary",
      "colFormat" : "",
      "displayIndex" : 0
    }, {
      "srcTgtColId" : 5316394,
      "ruleClsPropId" : 5316377,
      "srcTrgColName" : "birthd",
      "srcTrgColDataType" : "DATE",
      "colFlagType" : "src",
      "srcTrgColVisible" : 0,
      "joinList" : null,
      "mapColName" : "birthd",
      "colFormat" : "",
      "displayIndex" : 0
    }, {
      "srcTgtColId" : 5316395,
      "ruleClsPropId" : 5316377,
      "srcTrgColName" : "hired",
      "srcTrgColDataType" : "TIMESTAMP",
      "colFlagType" : "src",
      "srcTrgColVisible" : 0,
      "joinList" : null,
      "mapColName" : "hired",
      "colFormat" : "",
      "displayIndex" : 0
    }, {
      "srcTgtColId" : 5316396,
      "ruleClsPropId" : 5316377,
      "srcTrgColName" : "lname",
      "srcTrgColDataType" : "VARCHAR2",
      "colFlagType" : "src",
      "srcTrgColVisible" : 0,
      "joinList" : null,
      "mapColName" : "lname",
      "colFormat" : "",
      "displayIndex" : 0
    }, {
      "srcTgtColId" : 5316397,
      "ruleClsPropId" : 5316377,
      "srcTrgColName" : "fname",
      "srcTrgColDataType" : "VARCHAR2",
      "colFlagType" : "src",
      "srcTrgColVisible" : 0,
      "joinList" : null,
      "mapColName" : "fname",
      "colFormat" : "",
      "displayIndex" : 0
    }, {
      "srcTgtColId" : 5316398,
      "ruleClsPropId" : 5316377,
      "srcTrgColName" : "address",
      "srcTrgColDataType" : "VARCHAR2",
      "colFlagType" : "src",
      "srcTrgColVisible" : 0,
      "joinList" : null,
      "mapColName" : "address",
      "colFormat" : "",
      "displayIndex" : 0
    }, {
      "srcTgtColId" : 5316399,
      "ruleClsPropId" : 5316377,
      "srcTrgColName" : "city",
      "srcTrgColDataType" : "VARCHAR2",
      "colFlagType" : "src",
      "srcTrgColVisible" : 0,
      "joinList" : null,
      "mapColName" : "city",
      "colFormat" : "",
      "displayIndex" : 0
    }, {
      "srcTgtColId" : 5316400,
      "ruleClsPropId" : 5316377,
      "srcTrgColName" : "state",
      "srcTrgColDataType" : "VARCHAR2",
      "colFlagType" : "src",
      "srcTrgColVisible" : 0,
      "joinList" : null,
      "mapColName" : "state",
      "colFormat" : "",
      "displayIndex" : 0
    }, {
      "srcTgtColId" : 5316401,
      "ruleClsPropId" : 5316377,
      "srcTrgColName" : "hphone",
      "srcTrgColDataType" : "VARCHAR2",
      "colFlagType" : "src",
      "srcTrgColVisible" : 0,
      "joinList" : null,
      "mapColName" : "hphone",
      "colFormat" : "",
      "displayIndex" : 0
    }, {
      "srcTgtColId" : 5316402,
      "ruleClsPropId" : 5316377,
      "srcTrgColName" : "ssn",
      "srcTrgColDataType" : "NUMBER",
      "colFlagType" : "src",
      "srcTrgColVisible" : 0,
      "joinList" : null,
      "mapColName" : "ssn",
      "colFormat" : "",
      "displayIndex" : 0
    }, {
      "srcTgtColId" : 5316408,
      "ruleClsPropId" : 5316403,
      "srcTrgColName" : "cnt",
      "srcTrgColDataType" : "String",
      "colFlagType" : "tgt",
      "srcTrgColVisible" : 0,
      "joinList" : null,
      "mapColName" : "cnt",
      "colFormat" : "",
      "displayIndex" : 0
    } ],
    "colMapList" : [ {
      "colMapId" : 5316409,
      "srcColId" : 5316386,
      "trgColId" : 5316408,
      "colMapType" : "join",
      "srcColName" : "staffid",
      "tgtColName" : "cnt",
      "colMapExpr" : "cnt=staffid",
      "srcTrgColMapVisible" : 0,
      "displayIndex" : 0
    } ],
    "objectVOList" : null,
    "srcCount" : null,
    "trgCount" : null,
    "srcMissing" : null,
    "trgMissing" : null,
    "commonRows" : null,
    "classResult" : null,
    "classStatus" : null,
    "resultType" : null,
    "showErrorData" : null,
    "reportXlsx" : null,
    "ruleParameter" : "",
    "classCreatedBy" : 0,
    "classModifydBy" : 0,
    "classCreateDate" : null,
    "classModifyDate" : null,
    "exprVOList" : [ {
      "exprID" : 5316410,
      "exprLogID" : 0,
      "exprName" : "e_staffid",
      "expression" : "S.staffid == null",
      "result" : "Pass",
      "exprType" : "5",
      "exprVisible" : 1,
      "exprIndex" : 0,
      "ruleId" : 5316361,
      "ruleInstanceId" : 0,
      "ruleClassId" : 5316362,
      "ruleName" : null,
      "trueCount" : null,
      "falseCount" : null,
      "errCount" : null,
      "exprOrg" : null,
      "tc" : null,
      "fc" : null,
      "er" : null,
      "name" : null,
      "ve" : 0,
      "exporg" : null
    }, {
      "exprID" : 5316411,
      "exprLogID" : 0,
      "exprName" : "e_sex",
      "expression" : "S.sex == null",
      "result" : "Pass",
      "exprType" : "5",
      "exprVisible" : 1,
      "exprIndex" : 1,
      "ruleId" : 5316361,
      "ruleInstanceId" : 0,
      "ruleClassId" : 5316362,
      "ruleName" : null,
      "trueCount" : null,
      "falseCount" : null,
      "errCount" : null,
      "exprOrg" : null,
      "tc" : null,
      "fc" : null,
      "er" : null,
      "name" : null,
      "ve" : 0,
      "exporg" : null
    }, {
      "exprID" : 5316412,
      "exprLogID" : 0,
      "exprName" : "e_jobcode",
      "expression" : "S.jobcode == null",
      "result" : "Pass",
      "exprType" : "5",
      "exprVisible" : 1,
      "exprIndex" : 2,
      "ruleId" : 5316361,
      "ruleInstanceId" : 0,
      "ruleClassId" : 5316362,
      "ruleName" : null,
      "trueCount" : null,
      "falseCount" : null,
      "errCount" : null,
      "exprOrg" : null,
      "tc" : null,
      "fc" : null,
      "er" : null,
      "name" : null,
      "ve" : 0,
      "exporg" : null
    }, {
      "exprID" : 5316413,
      "exprLogID" : 0,
      "exprName" : "e_company",
      "expression" : "S.company == null",
      "result" : "Pass",
      "exprType" : "5",
      "exprVisible" : 1,
      "exprIndex" : 3,
      "ruleId" : 5316361,
      "ruleInstanceId" : 0,
      "ruleClassId" : 5316362,
      "ruleName" : null,
      "trueCount" : null,
      "falseCount" : null,
      "errCount" : null,
      "exprOrg" : null,
      "tc" : null,
      "fc" : null,
      "er" : null,
      "name" : null,
      "ve" : 0,
      "exporg" : null
    }, {
      "exprID" : 5316414,
      "exprLogID" : 0,
      "exprName" : "e_salary",
      "expression" : "S.salary == null",
      "result" : "Pass",
      "exprType" : "5",
      "exprVisible" : 1,
      "exprIndex" : 4,
      "ruleId" : 5316361,
      "ruleInstanceId" : 0,
      "ruleClassId" : 5316362,
      "ruleName" : null,
      "trueCount" : null,
      "falseCount" : null,
      "errCount" : null,
      "exprOrg" : null,
      "tc" : null,
      "fc" : null,
      "er" : null,
      "name" : null,
      "ve" : 0,
      "exporg" : null
    }, {
      "exprID" : 5316415,
      "exprLogID" : 0,
      "exprName" : "e_bonus",
      "expression" : "S.bonus == null",
      "result" : "Pass",
      "exprType" : "5",
      "exprVisible" : 1,
      "exprIndex" : 5,
      "ruleId" : 5316361,
      "ruleInstanceId" : 0,
      "ruleClassId" : 5316362,
      "ruleName" : null,
      "trueCount" : null,
      "falseCount" : null,
      "errCount" : null,
      "exprOrg" : null,
      "tc" : null,
      "fc" : null,
      "er" : null,
      "name" : null,
      "ve" : 0,
      "exporg" : null
    }, {
      "exprID" : 5316416,
      "exprLogID" : 0,
      "exprName" : "e_comm",
      "expression" : "S.comm == null",
      "result" : "Pass",
      "exprType" : "5",
      "exprVisible" : 1,
      "exprIndex" : 6,
      "ruleId" : 5316361,
      "ruleInstanceId" : 0,
      "ruleClassId" : 5316362,
      "ruleName" : null,
      "trueCount" : null,
      "falseCount" : null,
      "errCount" : null,
      "exprOrg" : null,
      "tc" : null,
      "fc" : null,
      "er" : null,
      "name" : null,
      "ve" : 0,
      "exporg" : null
    }, {
      "exprID" : 5316417,
      "exprLogID" : 0,
      "exprName" : "e_totalsalary",
      "expression" : "S.totalsalary == null",
      "result" : "Pass",
      "exprType" : "5",
      "exprVisible" : 1,
      "exprIndex" : 7,
      "ruleId" : 5316361,
      "ruleInstanceId" : 0,
      "ruleClassId" : 5316362,
      "ruleName" : null,
      "trueCount" : null,
      "falseCount" : null,
      "errCount" : null,
      "exprOrg" : null,
      "tc" : null,
      "fc" : null,
      "er" : null,
      "name" : null,
      "ve" : 0,
      "exporg" : null
    }, {
      "exprID" : 5316418,
      "exprLogID" : 0,
      "exprName" : "e_birthd",
      "expression" : "S.birthd == null",
      "result" : "Pass",
      "exprType" : "5",
      "exprVisible" : 1,
      "exprIndex" : 8,
      "ruleId" : 5316361,
      "ruleInstanceId" : 0,
      "ruleClassId" : 5316362,
      "ruleName" : null,
      "trueCount" : null,
      "falseCount" : null,
      "errCount" : null,
      "exprOrg" : null,
      "tc" : null,
      "fc" : null,
      "er" : null,
      "name" : null,
      "ve" : 0,
      "exporg" : null
    }, {
      "exprID" : 5316419,
      "exprLogID" : 0,
      "exprName" : "e_hired",
      "expression" : "S.hired == null",
      "result" : "Pass",
      "exprType" : "5",
      "exprVisible" : 1,
      "exprIndex" : 9,
      "ruleId" : 5316361,
      "ruleInstanceId" : 0,
      "ruleClassId" : 5316362,
      "ruleName" : null,
      "trueCount" : null,
      "falseCount" : null,
      "errCount" : null,
      "exprOrg" : null,
      "tc" : null,
      "fc" : null,
      "er" : null,
      "name" : null,
      "ve" : 0,
      "exporg" : null
    }, {
      "exprID" : 5316420,
      "exprLogID" : 0,
      "exprName" : "e_lname",
      "expression" : "S.lname == null",
      "result" : "Pass",
      "exprType" : "5",
      "exprVisible" : 1,
      "exprIndex" : 10,
      "ruleId" : 5316361,
      "ruleInstanceId" : 0,
      "ruleClassId" : 5316362,
      "ruleName" : null,
      "trueCount" : null,
      "falseCount" : null,
      "errCount" : null,
      "exprOrg" : null,
      "tc" : null,
      "fc" : null,
      "er" : null,
      "name" : null,
      "ve" : 0,
      "exporg" : null
    }, {
      "exprID" : 5316421,
      "exprLogID" : 0,
      "exprName" : "e_fname",
      "expression" : "S.fname == null",
      "result" : "Pass",
      "exprType" : "5",
      "exprVisible" : 1,
      "exprIndex" : 11,
      "ruleId" : 5316361,
      "ruleInstanceId" : 0,
      "ruleClassId" : 5316362,
      "ruleName" : null,
      "trueCount" : null,
      "falseCount" : null,
      "errCount" : null,
      "exprOrg" : null,
      "tc" : null,
      "fc" : null,
      "er" : null,
      "name" : null,
      "ve" : 0,
      "exporg" : null
    }, {
      "exprID" : 5316422,
      "exprLogID" : 0,
      "exprName" : "e_address",
      "expression" : "S.address == null",
      "result" : "Pass",
      "exprType" : "5",
      "exprVisible" : 1,
      "exprIndex" : 12,
      "ruleId" : 5316361,
      "ruleInstanceId" : 0,
      "ruleClassId" : 5316362,
      "ruleName" : null,
      "trueCount" : null,
      "falseCount" : null,
      "errCount" : null,
      "exprOrg" : null,
      "tc" : null,
      "fc" : null,
      "er" : null,
      "name" : null,
      "ve" : 0,
      "exporg" : null
    }, {
      "exprID" : 5316423,
      "exprLogID" : 0,
      "exprName" : "e_city",
      "expression" : "S.city == null",
      "result" : "Pass",
      "exprType" : "5",
      "exprVisible" : 1,
      "exprIndex" : 13,
      "ruleId" : 5316361,
      "ruleInstanceId" : 0,
      "ruleClassId" : 5316362,
      "ruleName" : null,
      "trueCount" : null,
      "falseCount" : null,
      "errCount" : null,
      "exprOrg" : null,
      "tc" : null,
      "fc" : null,
      "er" : null,
      "name" : null,
      "ve" : 0,
      "exporg" : null
    }, {
      "exprID" : 5316424,
      "exprLogID" : 0,
      "exprName" : "e_state",
      "expression" : "S.state == null",
      "result" : "Pass",
      "exprType" : "5",
      "exprVisible" : 1,
      "exprIndex" : 14,
      "ruleId" : 5316361,
      "ruleInstanceId" : 0,
      "ruleClassId" : 5316362,
      "ruleName" : null,
      "trueCount" : null,
      "falseCount" : null,
      "errCount" : null,
      "exprOrg" : null,
      "tc" : null,
      "fc" : null,
      "er" : null,
      "name" : null,
      "ve" : 0,
      "exporg" : null
    }, {
      "exprID" : 5316425,
      "exprLogID" : 0,
      "exprName" : "e_hphone",
      "expression" : "S.hphone == null",
      "result" : "Pass",
      "exprType" : "5",
      "exprVisible" : 1,
      "exprIndex" : 15,
      "ruleId" : 5316361,
      "ruleInstanceId" : 0,
      "ruleClassId" : 5316362,
      "ruleName" : null,
      "trueCount" : null,
      "falseCount" : null,
      "errCount" : null,
      "exprOrg" : null,
      "tc" : null,
      "fc" : null,
      "er" : null,
      "name" : null,
      "ve" : 0,
      "exporg" : null
    }, {
      "exprID" : 5316426,
      "exprLogID" : 0,
      "exprName" : "e_ssn",
      "expression" : "S.ssn == null",
      "result" : "Pass",
      "exprType" : "5",
      "exprVisible" : 1,
      "exprIndex" : 16,
      "ruleId" : 5316361,
      "ruleInstanceId" : 0,
      "ruleClassId" : 5316362,
      "ruleName" : null,
      "trueCount" : null,
      "falseCount" : null,
      "errCount" : null,
      "exprOrg" : null,
      "tc" : null,
      "fc" : null,
      "er" : null,
      "name" : null,
      "ve" : 0,
      "exporg" : null
    } ],
    "derivedvariablelist" : null
  }
}