{
  "ruleLogicalInfo" : {
    "id" : 1723360,
    "ruleInstanceId" : 0,
    "ruleDesc" : "",
    "execMode" : "report",
    "exitCode" : null,
    "folderId" : 1670998,
    "projectId" : 1670991,
    "ruleCode" : "1677129623359",
    "folderName" : "SQL_server-native",
    "folderType" : "RULE",
    "startTime" : null,
    "endTime" : null,
    "ruleName" : "V026-To check V8 validation rule with Having Clause_1677129623359",
    "displayName" : null,
    "rulePurpose" : "",
    "ruleTemplate" : null,
    "statusName" : null,
    "ruleCreatedBy" : 7,
    "ruleModifiedBy" : 0,
    "subjectAreaKey" : 0,
    "ruleStatus" : 1,
    "ruleCreateDate" : "2023-02-23 00:00:00",
    "ruleModifiedDate" : null,
    "enterpriseErrorCode" : "",
    "legalEntityId" : 1,
    "subjectAreaName" : null,
    "execNode" : "",
    "children" : null,
    "objVOList" : [ ],
    "tagVOList" : [ ],
    "ruleFlowList" : null,
    "ruleType" : "Warning",
    "auditExecutedByProcess" : null,
    "auditExecutionMedium" : null,
    "auditExecutionMediumName" : null,
    "comments" : null,
    "successMailUsers" : [ ],
    "failureMailUsers" : [ ],
    "successHeader" : "",
    "failureHeader" : "",
    "failureAttFlag" : 0,
    "successAttFlag" : 0,
    "srcConnId" : 1671001,
    "trgConnId" : 1671001,
    "srcSysGroupId" : 0,
    "trgSysGroupId" : 0,
    "srcConn" : "SC_window auth",
    "trgConn" : "SC_window auth",
    "elapseTime" : 0,
    "parameterId" : "",
    "type" : null,
    "isRuleExit" : null,
    "ruleCreatedByName" : "admin",
    "projectName" : "17.5.0_Wells_Fargo",
    "ruleModifiedByName" : null,
    "ruleClassId" : 1723361,
    "successBody" : "",
    "failureBody" : "",
    "templateId" : 206,
    "templateIdFail" : 206,
    "reportIdList" : [ ],
    "contextInstanceId" : 0,
    "srcConnFlag" : "REGULAR",
    "trgConnFlag" : "REGULAR",
    "degreeOfParallelism" : 0,
    "userComments" : null,
    "templateName" : "Rule Template-Default",
    "templateFailureName" : "Rule Template-Default",
    "objExists" : true
  },
  "rulePhysicalInfo" : {
    "objectName" : null,
    "ruleId" : 1723360,
    "reportRuleClassId" : 0,
    "ruleCId" : 0,
    "classVOList" : [ {
      "classId" : 3,
      "name" : null,
      "ruleClassId" : 1723361,
      "connType" : "",
      "execMode" : "report",
      "index" : 1,
      "classRun" : "com.ice.bpel.CompareData",
      "vid" : "CompareData11",
      "classObjName" : "ICE_1677064914138",
      "queryBuilderXML" : null,
      "connId" : 0,
      "resultType" : "rowcount",
      "connName" : null,
      "connUrl" : null,
      "connFullUrl" : null,
      "sysGrpId" : 0,
      "ruleId" : 0,
      "ruleName" : null,
      "ruleParameter" : null,
      "srcTrgMaplist" : [ {
        "colMapId" : 1723391,
        "srcColId" : 1723384,
        "trgColId" : 1723390,
        "colMapType" : "join",
        "srcColName" : "fname",
        "tgtColName" : "cnt",
        "colMapExpr" : "cnt=fname",
        "srcTrgColMapVisible" : 0,
        "displayIndex" : 0
      } ],
      "exprlist" : [ ],
      "derivedexprlist" : null,
      "paramsVOLst" : [ {
        "ruleClsPropID" : 1723364,
        "paramId" : 9,
        "paramMethod" : "setSourceObject",
        "paramValue" : "GetData11",
        "srcTrgTbllist" : null,
        "fileContent" : null
      }, {
        "ruleClsPropID" : 1723365,
        "paramId" : 10,
        "paramMethod" : "setTargetObject",
        "paramValue" : "GetData21",
        "srcTrgTbllist" : null,
        "fileContent" : null
      }, {
        "ruleClsPropID" : 1723366,
        "paramId" : 798,
        "paramMethod" : "setEngineType",
        "paramValue" : "V8",
        "srcTrgTbllist" : null,
        "fileContent" : null
      }, {
        "ruleClsPropID" : 1723367,
        "paramId" : 22,
        "paramMethod" : "setMaxRowCount",
        "paramValue" : "-1",
        "srcTrgTbllist" : null,
        "fileContent" : null
      }, {
        "ruleClsPropID" : 1723368,
        "paramId" : 23,
        "paramMethod" : "setMaxErrorCount",
        "paramValue" : "500",
        "srcTrgTbllist" : null,
        "fileContent" : null
      }, {
        "ruleClsPropID" : 1723369,
        "paramId" : 24,
        "paramMethod" : "setShowErrorData",
        "paramValue" : "No",
        "srcTrgTbllist" : null,
        "fileContent" : null
      }, {
        "ruleClsPropID" : 1723370,
        "paramId" : 72,
        "paramMethod" : "setTimeOut",
        "paramValue" : "",
        "srcTrgTbllist" : null,
        "fileContent" : null
      }, {
        "ruleClsPropID" : 1723371,
        "paramId" : 73,
        "paramMethod" : "setLoadDataFlag",
        "paramValue" : "No",
        "srcTrgTbllist" : null,
        "fileContent" : null
      }, {
        "ruleClsPropID" : 1723372,
        "paramId" : 465,
        "paramMethod" : "setReportXlsx",
        "paramValue" : "No",
        "srcTrgTbllist" : null,
        "fileContent" : null
      }, {
        "ruleClsPropID" : 1723373,
        "paramId" : 530,
        "paramMethod" : "setThresholdFlag",
        "paramValue" : "false",
        "srcTrgTbllist" : null,
        "fileContent" : null
      }, {
        "ruleClsPropID" : 1723374,
        "paramId" : 531,
        "paramMethod" : "setThresholdExpression",
        "paramValue" : "",
        "srcTrgTbllist" : [ ],
        "fileContent" : null
      } ],
      "bigDataExecMode" : null,
      "srcConnServer" : null,
      "trgConnServer" : null,
      "srcConnExecMode" : null,
      "trgConnExecMode" : null,
      "thresholdFlag" : null,
      "thresholdExpression" : null
    }, {
      "classId" : 1,
      "name" : null,
      "ruleClassId" : 1723362,
      "connType" : "DATABASE",
      "execMode" : "report",
      "index" : 0,
      "classRun" : "com.ice.bpel.GetData",
      "vid" : "GetData11",
      "classObjName" : "ICE_1677064914138",
      "queryBuilderXML" : null,
      "connId" : 1671001,
      "resultType" : "rowcount",
      "connName" : null,
      "connUrl" : null,
      "connFullUrl" : null,
      "sysGrpId" : 0,
      "ruleId" : 0,
      "ruleName" : null,
      "ruleParameter" : null,
      "srcTrgMaplist" : [ ],
      "exprlist" : [ ],
      "derivedexprlist" : null,
      "paramsVOLst" : [ {
        "ruleClsPropID" : 1723376,
        "paramId" : 6,
        "paramMethod" : "setQueryString",
        "paramValue" : "--select * from DBO.STAFF\n\nselect fname from DBO.STAFF group by fname having fname='RUSSELL'",
        "srcTrgTbllist" : [ {
          "srcTgtColId" : 1723384,
          "ruleClsPropId" : 1723376,
          "srcTrgColName" : "fname",
          "srcTrgColDataType" : "nvarchar",
          "colFlagType" : "src",
          "srcTrgColVisible" : 1,
          "joinList" : null,
          "mapColName" : null,
          "colFormat" : "",
          "displayIndex" : 11
        } ],
        "fileContent" : null
      }, {
        "ruleClsPropID" : 1723378,
        "paramId" : 16,
        "paramMethod" : "setConnId",
        "paramValue" : "1671001",
        "srcTrgTbllist" : null,
        "fileContent" : null
      }, {
        "ruleClsPropID" : 1723379,
        "paramId" : 337,
        "paramMethod" : "setIsStoredProcedure",
        "paramValue" : "false",
        "srcTrgTbllist" : null,
        "fileContent" : null
      }, {
        "ruleClsPropID" : 1723380,
        "paramId" : 84,
        "paramMethod" : "setOrderByStr",
        "paramValue" : "",
        "srcTrgTbllist" : [ ],
        "fileContent" : null
      }, {
        "ruleClsPropID" : 1723382,
        "paramId" : 82,
        "paramMethod" : "setAppendOrderBy",
        "paramValue" : "true",
        "srcTrgTbllist" : null,
        "fileContent" : null
      }, {
        "ruleClsPropID" : 1723383,
        "paramId" : 83,
        "paramMethod" : "setColumnsMInfo",
        "paramValue" : "fname^~^-9^~^nvarchar^~^2000^~^1",
        "srcTrgTbllist" : [ ],
        "fileContent" : null
      } ],
      "bigDataExecMode" : null,
      "srcConnServer" : null,
      "trgConnServer" : null,
      "srcConnExecMode" : null,
      "trgConnExecMode" : null,
      "thresholdFlag" : null,
      "thresholdExpression" : null
    }, {
      "classId" : 1,
      "name" : null,
      "ruleClassId" : 1723363,
      "connType" : "DATABASE",
      "execMode" : "report",
      "index" : 0,
      "classRun" : "com.ice.bpel.GetData",
      "vid" : "GetData21",
      "classObjName" : "ICE_1677064914138",
      "queryBuilderXML" : null,
      "connId" : 1671001,
      "resultType" : "rowcount",
      "connName" : null,
      "connUrl" : null,
      "connFullUrl" : null,
      "sysGrpId" : 0,
      "ruleId" : 0,
      "ruleName" : null,
      "ruleParameter" : null,
      "srcTrgMaplist" : [ ],
      "exprlist" : [ ],
      "derivedexprlist" : null,
      "paramsVOLst" : [ {
        "ruleClsPropID" : 1723385,
        "paramId" : 6,
        "paramMethod" : "setQueryString",
        "paramValue" : "select 1 as cnt",
        "srcTrgTbllist" : [ {
          "srcTgtColId" : 1723390,
          "ruleClsPropId" : 1723385,
          "srcTrgColName" : "cnt",
          "srcTrgColDataType" : "String",
          "colFlagType" : "tgt",
          "srcTrgColVisible" : 0,
          "joinList" : null,
          "mapColName" : null,
          "colFormat" : "",
          "displayIndex" : 0
        } ],
        "fileContent" : null
      }, {
        "ruleClsPropID" : 1723387,
        "paramId" : 83,
        "paramMethod" : "setColumnsMInfo",
        "paramValue" : "cnt^~^12^~^String^~^20^~^1",
        "srcTrgTbllist" : [ ],
        "fileContent" : null
      }, {
        "ruleClsPropID" : 1723388,
        "paramId" : 16,
        "paramMethod" : "setConnId",
        "paramValue" : "1671001",
        "srcTrgTbllist" : null,
        "fileContent" : null
      }, {
        "ruleClsPropID" : 1723389,
        "paramId" : 82,
        "paramMethod" : "setAppendOrderBy",
        "paramValue" : "false",
        "srcTrgTbllist" : null,
        "fileContent" : null
      } ],
      "bigDataExecMode" : null,
      "srcConnServer" : null,
      "trgConnServer" : null,
      "srcConnExecMode" : null,
      "trgConnExecMode" : null,
      "thresholdFlag" : null,
      "thresholdExpression" : null
    } ],
    "srcTrgTbllist" : [ {
      "srcTgtColId" : 1723384,
      "ruleClsPropId" : 1723376,
      "srcTrgColName" : "fname",
      "srcTrgColDataType" : "nvarchar",
      "colFlagType" : "src",
      "srcTrgColVisible" : 1,
      "joinList" : null,
      "mapColName" : "fname",
      "colFormat" : "",
      "displayIndex" : 11
    }, {
      "srcTgtColId" : 1723390,
      "ruleClsPropId" : 1723385,
      "srcTrgColName" : "cnt",
      "srcTrgColDataType" : "String",
      "colFlagType" : "tgt",
      "srcTrgColVisible" : 0,
      "joinList" : null,
      "mapColName" : "cnt",
      "colFormat" : "",
      "displayIndex" : 0
    } ],
    "colMapList" : [ {
      "colMapId" : 1723391,
      "srcColId" : 1723384,
      "trgColId" : 1723390,
      "colMapType" : "join",
      "srcColName" : "fname",
      "tgtColName" : "cnt",
      "colMapExpr" : "cnt=fname",
      "srcTrgColMapVisible" : 0,
      "displayIndex" : 0
    } ],
    "objectVOList" : null,
    "srcCount" : null,
    "trgCount" : null,
    "srcMissing" : null,
    "trgMissing" : null,
    "commonRows" : null,
    "classResult" : null,
    "classStatus" : null,
    "resultType" : null,
    "showErrorData" : null,
    "reportXlsx" : null,
    "ruleParameter" : "",
    "classCreatedBy" : 0,
    "classModifydBy" : 0,
    "classCreateDate" : null,
    "classModifyDate" : null,
    "exprVOList" : [ ],
    "derivedvariablelist" : null
  }
}